scipy/__config__.py
scipy/__init__.py
scipy/_distributor_init.py
scipy/conftest.py
scipy/linalg.pxd
scipy/optimize.pxd
scipy/special.pxd
scipy/version.py
scipy/_lib/__init__.py
scipy/_lib/_array_api.py
scipy/_lib/_bunch.py
scipy/_lib/_ccallback.py
scipy/_lib/_ccallback_c.cpython-312.so
scipy/_lib/_disjoint_set.py
scipy/_lib/_docscrape.py
scipy/_lib/_elementwise_iterative_method.py
scipy/_lib/_finite_differences.py
scipy/_lib/_fpumode.cpython-312.so
scipy/_lib/_gcutils.py
scipy/_lib/_pep440.py
scipy/_lib/_test_ccallback.cpython-312.so
scipy/_lib/_test_deprecation_call.cpython-312.so
scipy/_lib/_test_deprecation_def.cpython-312.so
scipy/_lib/_testutils.py
scipy/_lib/_threadsafety.py
scipy/_lib/_tmpdirs.py
scipy/_lib/_util.py
scipy/_lib/decorator.py
scipy/_lib/deprecation.py
scipy/_lib/doccer.py
scipy/_lib/messagestream.cpython-312.so
scipy/_lib/uarray.py
scipy/_lib/_uarray/LICENSE
scipy/_lib/_uarray/__init__.py
scipy/_lib/_uarray/_backend.py
scipy/_lib/_uarray/_uarray.cpython-312.so
scipy/_lib/array_api_compat/__init__.py
scipy/_lib/array_api_compat/_internal.py
scipy/_lib/array_api_compat/common/__init__.py
scipy/_lib/array_api_compat/common/_aliases.py
scipy/_lib/array_api_compat/common/_fft.py
scipy/_lib/array_api_compat/common/_helpers.py
scipy/_lib/array_api_compat/common/_linalg.py
scipy/_lib/array_api_compat/common/_typing.py
scipy/_lib/array_api_compat/cupy/__init__.py
scipy/_lib/array_api_compat/cupy/_aliases.py
scipy/_lib/array_api_compat/cupy/_typing.py
scipy/_lib/array_api_compat/cupy/fft.py
scipy/_lib/array_api_compat/cupy/linalg.py
scipy/_lib/array_api_compat/dask/__init__.py
scipy/_lib/array_api_compat/dask/array/__init__.py
scipy/_lib/array_api_compat/dask/array/_aliases.py
scipy/_lib/array_api_compat/dask/array/linalg.py
scipy/_lib/array_api_compat/numpy/__init__.py
scipy/_lib/array_api_compat/numpy/_aliases.py
scipy/_lib/array_api_compat/numpy/_typing.py
scipy/_lib/array_api_compat/numpy/fft.py
scipy/_lib/array_api_compat/numpy/linalg.py
scipy_aipy-1.14.1.dist-info/METADATA
scipy_aipy-1.14.1.dist-info/WHEEL
scipy_aipy-1.14.1.dist-info/top_level.txt
scipy_aipy-1.14.1.dist-info/RECORD
